pixelate/__init__.py
pixelate/fast/filters.py
pixelate/fast/pixel_ops.py
pixelate/fast/transformations.py
pixelate/slow/filters.py
pixelate/slow/pixel_ops.py
pixelate/slow/transformations.py
pixelate/utils/__init__.py
pixelate/utils/helpers.py
pixelate/utils/image_io.py
pixelatelib-0.1.0.dist-info/licenses/LICENSE
pixelatelib-0.1.0.dist-info/METADATA
pixelatelib-0.1.0.dist-info/WHEEL
pixelatelib-0.1.0.dist-info/top_level.txt
pixelatelib-0.1.0.dist-info/RECORD
