Metadata-Version: 2.4
Name: pixelatelib
Version: 0.1.0
Summary: Learn image processing by building it. A NumPy-based library that exposes both naive and optimized algorithms for side-by-side understanding.
Author-email: Montasar Dridi <montasardridi34@gmail.com>
License: MIT
Project-URL: Homepage, https://github.com/montasardridi/pixelate
Project-URL: Source, https://github.com/montasardridi/pixelate
Classifier: Programming Language :: Python :: 3
Requires-Python: >=3.10
License-File: LICENSE
Requires-Dist: numpy==2.2.0
Requires-Dist: Pillow==11.1.0
Provides-Extra: dev
Requires-Dist: opencv-python; extra == "dev"
Requires-Dist: pytest; extra == "dev"
Dynamic: license-file
